{"_type":"export","__export_format":4,"__export_date":"2023-01-25T12:04:08.778Z","__export_source":"insomnia.desktop.app:v2022.7.5","resources":[{"_id":"req_f0edc707dd0c4268b3e87a4e822bb0a2","parentId":"fld_c2a9541ca07d42be9d9565693e6471b7","modified":1674648170692,"created":1674565562503,"url":"http://localhost:4500/pedidos/update-finalizado","name":"Edita hora de entrega","description":"","method":"PUT","body":{"mimeType":"application/json","text":"{\n\t\"id_pedido\":4,\n\t\"entregador\":2\n}"},"parameters":[],"headers":[{"name":"Content-Type","value":"application/json"}],"authentication":{},"metaSortKey":-1674565562503,"isPrivate":false,"settingStoreCookies":true,"settingSendCookies":true,"settingDisableRenderRequestBody":false,"settingEncodeUrl":true,"settingRebuildPath":true,"settingFollowRedirects":"global","_type":"request"},{"_id":"fld_c2a9541ca07d42be9d9565693e6471b7","parentId":"wrk_9368b9d7f46d4ba99bd8603776b383eb","modified":1674559237952,"created":1674559237952,"name":"Pedidos","description":"","environment":{},"environmentPropertyOrder":null,"metaSortKey":-1674559237952,"_type":"request_group"},{"_id":"wrk_9368b9d7f46d4ba99bd8603776b383eb","parentId":null,"modified":1674558620542,"created":1674558620542,"name":"LanchinDoJOKA","description":"","scope":"collection","_type":"workspace"},{"_id":"req_d2abd2b8866540fbb1c1aace53f7b31d","parentId":"fld_c2a9541ca07d42be9d9565693e6471b7","modified":1674648145139,"created":1674565475312,"url":"http://localhost:4500/pedidos/update-entregador","name":"Edita hora execução","description":"","method":"PUT","body":{"mimeType":"application/json","text":"{\n\t\"id_pedido\":4\n}"},"parameters":[],"headers":[{"name":"Content-Type","value":"application/json"}],"authentication":{},"metaSortKey":-1674565475312,"isPrivate":false,"settingStoreCookies":true,"settingSendCookies":true,"settingDisableRenderRequestBody":false,"settingEncodeUrl":true,"settingRebuildPath":true,"settingFollowRedirects":"global","_type":"request"},{"_id":"req_0e86a47f28be4e6fa95689ba7aef8e8a","parentId":"fld_c2a9541ca07d42be9d9565693e6471b7","modified":1674566316897,"created":1674564387716,"url":"http://localhost:4500/pedidos/update/","name":"Edita Pedido","description":"","method":"PUT","body":{"mimeType":"application/json","text":"{\n\t\"id_pedido\":30,\n\t\"cliente\":\"Lucas Pica seca\",\n\t\"endereco\":\"Rua dos ArcCornos\",\n\t\"produto\":\"1 BRAHMA 1 CONSOLO\"\n}"},"parameters":[],"headers":[{"name":"Content-Type","value":"application/json"}],"authentication":{},"metaSortKey":-1674564387716,"isPrivate":false,"settingStoreCookies":true,"settingSendCookies":true,"settingDisableRenderRequestBody":false,"settingEncodeUrl":true,"settingRebuildPath":true,"settingFollowRedirects":"global","_type":"request"},{"_id":"req_20ecf3d824bd409f9dff3af516b87ba4","parentId":"fld_c2a9541ca07d42be9d9565693e6471b7","modified":1674561292670,"created":1674561254068,"url":"http://localhost:4500/pedidos/delete/2","name":"Deletar Produto","description":"","method":"DELETE","body":{},"parameters":[],"headers":[],"authentication":{},"metaSortKey":-1674561254068,"isPrivate":false,"settingStoreCookies":true,"settingSendCookies":true,"settingDisableRenderRequestBody":false,"settingEncodeUrl":true,"settingRebuildPath":true,"settingFollowRedirects":"global","_type":"request"},{"_id":"req_59aeb546fb194d79927d076b0f769792","parentId":"fld_c2a9541ca07d42be9d9565693e6471b7","modified":1674648100506,"created":1674559737837,"url":"http://localhost:4500/pedidos/create","name":"Cria Pedido","description":"","method":"POST","body":{"mimeType":"application/json","text":"{\n\t\"cliente\":\"Lucas Na Seca\",\n\t\"endereco\":\"Rua dos Adms\",\n\t\"produto\":\"1 BRAHMA\"\n}"},"parameters":[],"headers":[{"name":"Content-Type","value":"application/json"}],"authentication":{},"metaSortKey":-1674559737837,"isPrivate":false,"settingStoreCookies":true,"settingSendCookies":true,"settingDisableRenderRequestBody":false,"settingEncodeUrl":true,"settingRebuildPath":true,"settingFollowRedirects":"global","_type":"request"},{"_id":"req_0aca3f103a5f46fabfe9877fe148d912","parentId":"fld_c2a9541ca07d42be9d9565693e6471b7","modified":1674644682111,"created":1674644446626,"url":"http://localhost:4500/read/vw_finalizado","name":"vw_finalizados","description":"","method":"GET","body":{},"parameters":[],"headers":[],"authentication":{},"metaSortKey":-1674559707422.625,"isPrivate":false,"settingStoreCookies":true,"settingSendCookies":true,"settingDisableRenderRequestBody":false,"settingEncodeUrl":true,"settingRebuildPath":true,"settingFollowRedirects":"global","_type":"request"},{"_id":"req_2288a76712454301a42a515c3973ad16","parentId":"fld_c2a9541ca07d42be9d9565693e6471b7","modified":1674644655476,"created":1674644443186,"url":"http://localhost:4500/read/vw_entrega","name":"vw_entrega","description":"","method":"GET","body":{},"parameters":[],"headers":[],"authentication":{},"metaSortKey":-1674559677008.25,"isPrivate":false,"settingStoreCookies":true,"settingSendCookies":true,"settingDisableRenderRequestBody":false,"settingEncodeUrl":true,"settingRebuildPath":true,"settingFollowRedirects":"global","_type":"request"},{"_id":"req_6e8ec8a5d05e4b199cad96ea3dae53b6","parentId":"fld_c2a9541ca07d42be9d9565693e6471b7","modified":1674644622555,"created":1674644438074,"url":"http://localhost:4500/read/vw_cozinha","name":"vw_cozinha","description":"","method":"GET","body":{},"parameters":[],"headers":[],"authentication":{},"metaSortKey":-1674559616179.5,"isPrivate":false,"settingStoreCookies":true,"settingSendCookies":true,"settingDisableRenderRequestBody":false,"settingEncodeUrl":true,"settingRebuildPath":true,"settingFollowRedirects":"global","_type":"request"},{"_id":"req_5ea91a634af14f5cba7d89fe11dce008","parentId":"fld_c2a9541ca07d42be9d9565693e6471b7","modified":1674644473426,"created":1674559494522,"url":"http://localhost:4500/pedidos/read/65","name":"Lista Pedido por ID","description":"","method":"GET","body":{},"parameters":[],"headers":[],"authentication":{},"metaSortKey":-1674559494522,"isPrivate":false,"settingStoreCookies":true,"settingSendCookies":true,"settingDisableRenderRequestBody":false,"settingEncodeUrl":true,"settingRebuildPath":true,"settingFollowRedirects":"global","_type":"request"},{"_id":"req_26ec8517fc23440db8e9dee2e16a0ef9","parentId":"fld_c2a9541ca07d42be9d9565693e6471b7","modified":1674559454696,"created":1674559242712,"url":"http://localhost:4500/pedidos/read","name":"Lista Pedidos","description":"","method":"GET","body":{"mimeType":"application/json","text":""},"parameters":[],"headers":[{"name":"Content-Type","value":"application/json"}],"authentication":{},"metaSortKey":-1674559242712,"isPrivate":false,"settingStoreCookies":true,"settingSendCookies":true,"settingDisableRenderRequestBody":false,"settingEncodeUrl":true,"settingRebuildPath":true,"settingFollowRedirects":"global","_type":"request"},{"_id":"req_2432513606424162b4a89a1b2f4f2372","parentId":"fld_ffb2ebac80324a3bb2bdeeeb2c5d4ed0","modified":1674647335829,"created":1674647051328,"url":"http://localhost:4500/entregadores/status_update","name":"Edita Status","description":"","method":"PUT","body":{"mimeType":"application/json","text":"{\n\t\"id_entregador\":2\n}"},"parameters":[],"headers":[{"name":"Content-Type","value":"application/json"}],"authentication":{},"metaSortKey":-1674647051328,"isPrivate":false,"settingStoreCookies":true,"settingSendCookies":true,"settingDisableRenderRequestBody":false,"settingEncodeUrl":true,"settingRebuildPath":true,"settingFollowRedirects":"global","_type":"request"},{"_id":"fld_ffb2ebac80324a3bb2bdeeeb2c5d4ed0","parentId":"wrk_9368b9d7f46d4ba99bd8603776b383eb","modified":1674559185049,"created":1674559185049,"name":"Entregador","description":"","environment":{},"environmentPropertyOrder":null,"metaSortKey":-1674559185049,"_type":"request_group"},{"_id":"req_9b1ef8943d7443a69cd598cad163a4e1","parentId":"fld_ffb2ebac80324a3bb2bdeeeb2c5d4ed0","modified":1674647162192,"created":1674646526897,"url":"http://localhost:4500/entregadores/disponivel","name":"DISPONÍVEIS","description":"","method":"GET","body":{},"parameters":[],"headers":[],"authentication":{},"metaSortKey":-1674646526897,"isPrivate":false,"settingStoreCookies":true,"settingSendCookies":true,"settingDisableRenderRequestBody":false,"settingEncodeUrl":true,"settingRebuildPath":true,"settingFollowRedirects":"global","_type":"request"},{"_id":"req_f16b5668742f461aa36cfbff723b44ae","parentId":"fld_ffb2ebac80324a3bb2bdeeeb2c5d4ed0","modified":1674646583872,"created":1674559211111,"url":"http://localhost:4500/entregadores/read","name":"Lista Entregadores","description":"","method":"GET","body":{},"parameters":[],"headers":[],"authentication":{},"metaSortKey":-1674559211111,"isPrivate":false,"settingStoreCookies":true,"settingSendCookies":true,"settingDisableRenderRequestBody":false,"settingEncodeUrl":true,"settingRebuildPath":true,"settingFollowRedirects":"global","_type":"request"},{"_id":"req_9f574c06917941599d46021e336e6138","parentId":"fld_ffb2ebac80324a3bb2bdeeeb2c5d4ed0","modified":1674559189801,"created":1674559075782,"url":"http://localhost:4500/entregadores/read/3","name":"lista  Entregador por ID","description":"","method":"GET","body":{},"parameters":[],"headers":[],"authentication":{},"metaSortKey":-1674559075782,"isPrivate":false,"settingStoreCookies":true,"settingSendCookies":true,"settingDisableRenderRequestBody":false,"settingEncodeUrl":true,"settingRebuildPath":true,"settingFollowRedirects":"global","_type":"request"},{"_id":"env_eee219e531a2a9f127c3a5da64906ed7e3d783a7","parentId":"wrk_9368b9d7f46d4ba99bd8603776b383eb","modified":1674558620552,"created":1674558620552,"name":"Base Environment","data":{},"dataPropertyOrder":null,"color":null,"isPrivate":false,"metaSortKey":1674558620552,"_type":"environment"},{"_id":"jar_eee219e531a2a9f127c3a5da64906ed7e3d783a7","parentId":"wrk_9368b9d7f46d4ba99bd8603776b383eb","modified":1674558620556,"created":1674558620556,"name":"Default Jar","cookies":[],"_type":"cookie_jar"},{"_id":"spc_5ba3b186e88b4971a1ad09f1509e9fff","parentId":"wrk_9368b9d7f46d4ba99bd8603776b383eb","modified":1674558620543,"created":1674558620543,"fileName":"LanchinDoJOKA","contents":"","contentType":"yaml","_type":"api_spec"}]}